Lab09/NextPClogic.v
module NextPClogic(NextPC, CurrentPC, SignExtImm64, Branch, ALUZero, Uncondbranch); 
   input [63:0] CurrentPC, SignExtImm64; 
   input 	Branch, ALUZero, Uncondbranch; 
   output [63:0] NextPC; 
   
   reg [63:0] temp;

   /* write your code here */ 
   
   always @(*) begin
      temp = CurrentPC;
      if (Uncondbranch) begin // B
         temp = CurrentPC + (SignExtImm64);
      end
      else if(Branch && ALUZero) begin //CBZ
         temp = CurrentPC  + (SignExtImm64);
      end
      else begin // normal increment
         temp = CurrentPC + 4;
      end
   end
   
   assign NextPC = temp; // set the output wire to the computed value
   


endmodule

Lab09/DataMemory.v
`timescale 1ns / 1ps

`define SIZE 1024

module DataMemory(ReadData , Address , WriteData , MemoryRead , MemoryWrite , Clock);
   input [63:0]      WriteData;
   input [63:0]      Address;
   input             Clock, MemoryRead, MemoryWrite;
   output reg [63:0] ReadData;

   reg [7:0] 	     memBank [`SIZE-1:0];
   


   // This task is used to write arbitrary data to the Data Memory by
   // the intialization block.
   task initset;
      input [63:0] addr;
      input [63:0] data;
      begin
	 memBank[addr] =  data[63:56] ; // Big-endian for the win...
	 memBank[addr+1] =  data[55:48];
	 memBank[addr+2] =  data[47:40];
	 memBank[addr+3] =  data[39:32];
	 memBank[addr+4] =  data[31:24];
	 memBank[addr+5] =  data[23:16];
	 memBank[addr+6] =  data[15:8];
	 memBank[addr+7] =  data[7:0];
      end
   endtask


   initial
     begin
        // preseting some data in the data memory used by test #1

        // Address 0x0 gets 0x1
        initset( 64'h0,  64'h1);  //Counter variable
        initset( 64'h8,  64'ha);  //Part of mask
        initset( 64'h10, 64'h5);  //Other part of mask
        initset( 64'h18, 64'h0ffbea7deadbeeff); //big constant
        initset( 64'h20, 64'h0); //clearing space

        // Add any data you need for your tests here.

     end

   // This always block reads the data memory and places a double word
   // on the ReadData bus.
   always @(posedge Clock)
     begin
        if(MemoryRead)
          begin
             ReadData[63:56] <=  memBank[Address];
             ReadData[55:48] <=  memBank[Address+1];
             ReadData[47:40] <=  memBank[Address+2];
             ReadData[39:32] <=  memBank[Address+3];
             ReadData[31:24] <=  memBank[Address+4];
             ReadData[23:16] <=  memBank[Address+5];
             ReadData[15:8] <=  memBank[Address+6];
             ReadData[7:0] <=  memBank[Address+7];
          end
     end

   // This always block takes data from the WriteData bus and writes
   // it into the DataMemory.
   always @(posedge Clock)
     begin
        if(MemoryWrite)
          begin
             memBank[Address] <= #3 WriteData[63:56] ;
             memBank[Address+1] <= #3 WriteData[55:48];
             memBank[Address+2] <= #3 WriteData[47:40];
             memBank[Address+3] <= #3 WriteData[39:32];
             memBank[Address+4] <= #3 WriteData[31:24];
             memBank[Address+5] <= #3 WriteData[23:16];
             memBank[Address+6] <= #3 WriteData[15:8];
             memBank[Address+7] <= #3 WriteData[7:0];
             // Could be useful for debugging:
             // $display("Writing Address:%h Data:%h",Address, WriteData);
          end
     end
endmodule

Lab07/ALU.v
// Define constants

`define AND   4'b0000
`define OR    4'b0001
`define ADD   4'b0010
`define SUB   4'b0110
`define PassB 4'b0111


module ALU(BusW, BusA, BusB, ALUCtrl, Zero);
    
    output  [63:0] BusW;
    input   [63:0] BusA, BusB;
    input   [3:0] ALUCtrl;
    output  Zero;
    
    reg     [63:0] BusW;
    
    always @(ALUCtrl or BusA or BusB) begin
    // For each ALU action, do the appropriate response
        case(ALUCtrl)
            `AND: begin BusW = BusA & BusB; end // Bitwise AND
            `OR: begin BusW = BusA | BusB; end // Bitwise OR
            `ADD: begin BusW = BusA + BusB; end // ADD
            `SUB: begin BusW = BusA - BusB; end // SUB
            `PassB: begin BusW = BusB; end // Simply return B
        endcase
    end

    // Zero bit is based on output of BusW
    assign Zero = (BusW == 0);
endmodule

Lab09/MiniRegisterFile.v
module MiniRegisterFile(BusA, BusB, BusW, RA, RB, RW, RegWr, Clk);
    // outputs
    output [63:0] BusA;
    output [63:0] BusB;
    
    // inputs
    input [63:0] BusW;
    input [4:0] RA, RB, RW;
    input RegWr;
    input Clk;
    
    //intermediate
    reg [63:0] registers [31:0];
    
    // Set all registers to 0 at start
    //initial begin
        //$monitor("X9 = 0x%0h, X10 = 0x%0h, X11 = 0x%0h, X12 = 0x%0h", registers[9], registers[10], registers[11], registers[12]);
        ////#120; $display("BusWss = 0x%0h", BusW);
    //end


     
    // Send data from registers at RA and RB to BusA and BusB each
    assign BusA = (RA!=5'd31)?registers[RA]:64'b0;
    assign BusB = (RB!=5'd31)?registers[RB]:64'b0;
     
    always @ (negedge Clk) begin    
    
        if(RegWr && RW != 5'd31) begin
            // Write with delay of 3 tics
            registers[RW] <= BusW;
        end
    end
endmodule

Lab09/SignExtender_Example.v
`define I 3'b000
`define D 3'b001
`define B 3'b010
`define C 3'b011
`define Z 3'b100
module SignExtender_Example(BusImm, Imm16, Ctrl); 
   output [63:0] BusImm; 
   input [25:0]  Imm16; 
   input [2:0]	 Ctrl; 
   
   reg [63:0] BusImm; //reg so that we can set the output
   
   /*initial begin
     $monitor("[$monitor] Imm16 = 0x%0h, BusImm = 0x%0h", Imm16, BusImm);
   end*/
   
   
    always @(*) begin
        // For each ALU action, do the appropriate manipulation from MIPS green sheet
        case(Ctrl)
            `I: begin BusImm = {{52{Imm16[21]}}, Imm16[21:10]}; end //[21:10] is ALU immediatee
            `D: begin BusImm = {{55{Imm16[20]}}, Imm16[20:12]}; end //[20:12] is DT address
            `B: begin BusImm = {{36{Imm16[25]}}, Imm16[25:0], 2'b0}; end //[25:0] is BR address
            `C: begin BusImm = {{43{Imm16[23]}}, Imm16[23:5], 2'b0}; end //[23:5] is COND BR address
            `Z: begin BusImm = Imm16[20:5]<<(Imm16[22:21]*16);
            end
        endcase
    end
endmodule

Lab09/SingleCycleControl.v
`define OPCODE_ANDREG 11'b?0001010???
`define OPCODE_ORRREG 11'b?0101010???
`define OPCODE_ADDREG 11'b?0?01011???
`define OPCODE_SUBREG 11'b?1?01011???

`define OPCODE_ADDIMM 11'b?0?10001???
`define OPCODE_SUBIMM 11'b?1?10001???

`define OPCODE_MOVZ   11'b110100101??

`define OPCODE_B      11'b?00101?????
`define OPCODE_CBZ    11'b?011010????

`define OPCODE_LDUR   11'b??111000010
`define OPCODE_STUR   11'b??111000000

module control(
	       output reg 	reg2loc,
	       output reg 	alusrc,
	       output reg 	mem2reg,
	       output reg 	regwrite,
	       output reg 	memread,
	       output reg 	memwrite,
	       output reg 	branch,
	       output reg 	uncond_branch,
	       output reg [3:0] aluop,
	       output reg [2:0] signop,
	       input [10:0] 	opcode
	       );

   always @(*)
     begin
	casez (opcode)

          /* Add cases here for each instruction your processor supports */
	  //LDUR flags
	  `OPCODE_LDUR:
	    begin
               reg2loc       = 1'bx;
               alusrc        = 1'b1;
               mem2reg       = 1'b1;
               regwrite      = 1'b1;
               memread       = 1'b1;
               memwrite      = 1'b0;
               branch        = 1'b0;
               uncond_branch = 1'b0;
               aluop         = 4'b0010;
               signop        = 3'b01;
            end
	   
	  // STUR flags  
	  `OPCODE_STUR:
	    begin
               reg2loc       = 1'b1;
               alusrc        = 1'b1;
               mem2reg       = 1'bx;
               regwrite      = 1'b0;
               memread       = 1'b0;
               memwrite      = 1'b1;
               branch        = 1'b0;
               uncond_branch = 1'b0;
               aluop         = 4'b0010;
               signop        = 3'b01;
            end
	    
	  // CBZ Type Instructions  
	  `OPCODE_CBZ:
	    begin
               reg2loc       = 1'b1;
               alusrc        = 1'b0;
               mem2reg       = 1'bx;
               regwrite      = 1'b0;
               memread       = 1'b0;
               memwrite      = 1'b0;
               branch        = 1'b1;
               uncond_branch = 1'b0;
               aluop         = 4'b0111;
               signop        = 3'b11;
            end
	    
	  // B Type Instructions  
	  `OPCODE_B:
	    begin
               reg2loc       = 1'bx;
               alusrc        = 1'bx;
               mem2reg       = 1'bx;
               regwrite      = 1'b0;
               memread       = 1'b0;
               memwrite      = 1'b0;
               branch        = 1'bx;
               uncond_branch = 1'b1;
               aluop         = 4'bxxxx;
               signop        = 3'b10;
            end
	    
	  // R Type Instructions  
	  `OPCODE_ANDREG, `OPCODE_ORRREG, `OPCODE_ADDREG, `OPCODE_SUBREG:
	    begin
               reg2loc       = 1'b0;
               alusrc        = 1'b0;
               mem2reg       = 1'b0;
               regwrite      = 1'b1;
               memread       = 1'b0;
               memwrite      = 1'b0;
               branch        = 1'b0;
               uncond_branch = 1'b0;
               signop        = 3'b10;
	       casez (opcode)
		    `OPCODE_ANDREG: aluop = 4'b0000;
		    `OPCODE_ORRREG: aluop = 4'b0001;
		    `OPCODE_ADDREG: aluop = 4'b0010;
		    `OPCODE_SUBREG: aluop = 4'b0110;
	       endcase 
            end
	    
	  // I Type Instructions
	  `OPCODE_ADDIMM, `OPCODE_SUBIMM:
	    begin
               reg2loc       = 1'b0;
               alusrc        = 1'b1;
               mem2reg       = 1'b0;
               regwrite      = 1'b1;
               memread       = 1'b0;
               memwrite      = 1'b0;
               branch        = 1'b0;
               uncond_branch = 1'b0;
               signop        = 3'bxxx;
	       casez (opcode)
		    `OPCODE_ADDIMM: aluop = 4'b0010;
		    `OPCODE_SUBIMM: aluop = 4'b0110;
	       endcase 
            end
	    
	  // MOV type instructions
	    
	  `OPCODE_MOVZ:
	    begin
               reg2loc       = 1'bx;
               alusrc        = 1'b1;
               mem2reg       = 1'b0;
               regwrite      = 1'b1;
               memread       = 1'b0;
               memwrite      = 1'b0;
               branch        = 1'b0;
               uncond_branch = 1'b0;
	       aluop         = 4'b0111;
               signop        = 3'b100;
            end
	    
	  
          default:
            begin
               reg2loc       = 1'bx;
               alusrc        = 1'bx;
               mem2reg       = 1'bx;
               regwrite      = 1'b0;
               memread       = 1'b0;
               memwrite      = 1'b0;
               branch        = 1'b0;
               uncond_branch = 1'b0;
               aluop         = 4'bxxxx;
               signop        = 3'bxxx;
            end
	endcase
     end

endmodule

Lab09/InstructionMemory.v
`timescale 1ns / 1ps

`define OPCODE_MOVZ   9'b110100101
`define OPCODE_ORRREG 11'b00101010000
`define OPCODE_STUR   11'b11111000000
`define OPCODE_LDUR   11'b11111000010

/*
 * Module: InstructionMemory
 *
 * Implements read-only instruction memory
 * 
 */
module InstructionMemory(Data, Address);
   parameter T_rd = 20;
   parameter MemSize = 40;
   
   output [31:0] Data;
   input [63:0]  Address;
   reg [31:0] 	 Data;
   
   /*
    * ECEN 350 Processor Test Functions
    * Texas A&M University
    */
    
    reg [31:0] test;
    
    

   
   always @ (Address) begin

      case(Address)

	/* Test Program 1:
	 * Program loads constants from the data memory. Uses these constants to test
	 * the following instructions: LDUR, ORR, AND, CBZ, ADD, SUB, STUR and B.
	 * 
	 * Assembly code for test:
	 * 
	 * 0: LDUR X9, [XZR, 0x0]    //Load 1 into x9
	 * 4: LDUR X10, [XZR, 0x8]   //Load a into x10
	 * 8: LDUR X11, [XZR, 0x10]  //Load 5 into x11
	 * C: LDUR X12, [XZR, 0x18]  //Load big constant into x12
	 * 10: LDUR X13, [XZR, 0x20]  //load a 0 into X13
	 * 
	 * 14: ORR X10, X10, X11  //Create mask of 0xf
	 * 18: AND X12, X12, X10  //Mask off low order bits of big constant
	 * 
	 * loop:
	 * 1C: CBZ X12, end  //while X12 is not 0
	 * 20: ADD X13, X13, X9  //Increment counter in X13
	 * 24: SUB X12, X12, X9  //Decrement remainder of big constant in X12
	 * 28: B loop  //Repeat till X12 is 0
	 * 2C: STUR X13, [XZR, 0x20]  //store back the counter value into the memory location 0x20
	 */
	

	63'h000: Data = 32'hf84003e9;
	63'h004: Data = 32'hf84083ea;
	63'h008: Data = 32'hf84103eb;
	63'h00c: Data = 32'hf84183ec;
	63'h010: Data = 32'hf84203ed;
	63'h014: Data = 32'haa0b014a;
	63'h018: Data = 32'h8a0a018c;
	63'h01c: Data = 32'hb400008c;
	63'h020: Data = 32'h8b0901ad;
	63'h024: Data = 32'hcb09018c;
	63'h028: Data = 32'h17fffffd;
	63'h02c: Data = 32'hf80203ed;
	63'h030: Data = 32'hf84203ed;  //One last load to place stored value on memdbus for test checking
	
	63'h034: Data = {`OPCODE_MOVZ, 2'b11, 16'h1234, 5'd9}; //MOVZ 0xh1234 LSL 48 11010010 (11 11) 0xh1234 9
	63'h038: Data = {`OPCODE_MOVZ, 2'b10, 16'h5678, 5'd10}; //MOVK 0xh5678 LSL 32              10
	63'h03c: Data = {`OPCODE_MOVZ, 2'b01, 16'h9abc, 5'd11}; //MOVK 0xh9abc LSL 16            01
	63'h040: Data = {`OPCODE_MOVZ, 2'b00, 16'hdef0, 5'd12}; //MOVK 0xhdef0
	
	63'h044: Data = {`OPCODE_ORRREG, 5'd9, 6'd0, 5'd10, 5'd9}; // OR X9 X9 X10
	63'h048: Data = {`OPCODE_ORRREG, 5'd9, 6'd0, 5'd11, 5'd9}; // OR X9 X9 X10
	63'h04c: Data = {`OPCODE_ORRREG, 5'd9, 6'd0, 5'd12, 5'd9}; // OR X9 X9 X10
	
	63'h050: Data = {`OPCODE_STUR, 9'h28, 2'd0, 5'd31, 5'd9}; // STUR X9, [XZR, #0x28]
	63'h054: Data = {`OPCODE_LDUR, 9'h28, 2'd0, 5'd31, 5'd10}; // LDUR X10, [XZR, #0x28]	
	
	63'h058: Data = 32'hf84203ea;  //One last load to place stored value on memdbus for test checking				
					

	/* Add code for your tests here */

	
	default: Data = 32'hXXXXXXXX;
      endcase
   end
endmodule

Lab09/SingleCycleProc.v
module singlecycle(
		   input 	     resetl,
		   input [63:0]      startpc,
		   output reg [63:0] currentpc,
		   output [63:0]     MemtoRegOut,  // this should be
						   // attached to the
						   // output of the
						   // MemtoReg Mux
		   input 	     CLK
		   );

   // Next PC connections
   wire [63:0] 			     nextpc;       // The next PC, to be updated on clock cycle

   // Instruction Memory connections
   wire [31:0] 			     instruction;  // The current instruction

   // Parts of instruction
   wire [4:0] 			     rd;            // The destination register
   wire [4:0] 			     rm;            // Operand 1
   wire [4:0] 			     rn;            // Operand 2
   wire [10:0] 			     opcode;

   // Control wires
   wire [63:0] readOut;
   wire 			     reg2loc;
   wire 			     alusrc;
   wire 			     mem2reg;
   wire 			     regwrite;
   wire 			     memread;
   wire 			     memwrite;
   wire 			     branch;
   wire 			     uncond_branch;
   wire [3:0] 			     aluctrl;
   wire [2:0] 			     signop;

   // Register file connections
   wire [63:0] 			     regoutA;     // Output A
   wire [63:0] 			     regoutB;     // Output B

   // ALU connections
   wire [63:0] 			     aluout;
   wire 			     zero;

   // Sign Extender connections
   wire [63:0] 			     extimm;

   // PC update logic
   always @(negedge CLK)
     begin
        if (resetl)
          currentpc <= #3 nextpc;
        else
          currentpc <= #3 startpc;
     end

   // Parts of instruction
   assign rd = instruction[4:0];
   assign rm = instruction[9:5];
   assign rn = reg2loc ? instruction[4:0] : instruction[20:16];
   assign opcode = instruction[31:21];

   InstructionMemory imem(
			  .Data(instruction),
			  .Address(currentpc)
			  );

   control control(
		   .reg2loc(reg2loc),
		   .alusrc(alusrc),
		   .mem2reg(mem2reg),
		   .regwrite(regwrite),
		   .memread(memread),
		   .memwrite(memwrite),
		   .branch(branch),
		   .uncond_branch(uncond_branch),
		   .aluop(aluctrl),
		   .signop(signop),
		   .opcode(opcode)
		   );

   /*
    * Connect the remaining datapath elements below.
    * Do not forget any additional multiplexers that may be required.
    */
    
    SignExtender_Example see( //gives 64 bit for everything else
      .BusImm(extimm),
      .Imm16(instruction[25:0]),
      .Ctrl(signop)
    ); 
    
    /*Mux21 bget( 
    out(busB), 
    in(, 
    sel); */
    
    wire [63:0] rb;
    
    assign rb = (alusrc) ?  extimm : regoutB; //gives new regout depending on alusrc 
    
    MiniRegisterFile mrf(//gives BUS A and BUSB
      .BusA(regoutA),
      .BusB(regoutB),
      .BusW(MemtoRegOut),
      .RA(rm),
      .RB(rn),
      .RW(rd),
      .RegWr(regwrite),
      .Clk(CLK)
      );
    
    
    ALU alu(//Gives BusW
      .BusW(aluout),
      .BusA(regoutA),
      .BusB(rb),
      .ALUCtrl(aluctrl),
      .Zero(zero)
    );
    
    DataMemory dm(
      .ReadData(readOut),
      .Address(aluout),
      .WriteData(regoutB),
      .MemoryRead(memread),
      .MemoryWrite(memwrite),
      .Clock(CLK)
      );
    
   assign MemtoRegOut = (mem2reg) ? readOut : aluout;

    
    NextPClogic npl(
       .NextPC(nextpc),
       .CurrentPC(currentpc),
       .SignExtImm64(extimm),
       .Branch(branch),
       .ALUZero(zero),
       .Uncondbranch(uncond_branch)
    );
    



endmodule

Lab09/SingleCycleProcTest.v
`timescale 1ns / 1ps

`define STRLEN 32
`define HalfClockPeriod 60
`define ClockPeriod `HalfClockPeriod * 2

module SingleCycleProcTest_v;

   initial
     begin
        $dumpfile("singlecycle.vcd");
        $dumpvars;
     end

   // These tasks are used to check if a given test has passed and
   // confirm that all tests passed.
   task passTest;
      input [63:0] actualOut, expectedOut;
      input [`STRLEN*8:0] testType;
      inout [7:0] 	  passed;

      if(actualOut == expectedOut) begin $display ("%s passed", testType); passed = passed + 1; end
      else $display ("%s failed: 0x%x should be 0x%x", testType, actualOut, expectedOut);
   endtask

   task allPassed;
      input [7:0] passed;
      input [7:0] numTests;

      if(passed == numTests) $display ("All tests passed");
      else $display("Some tests failed: %d of %d passed", passed, numTests);
   endtask

   // Inputs
   reg 		  CLK;
   reg 		  Reset_L;
   reg [63:0] 	  startPC;
   reg [7:0] 	  passed;
   reg [15:0] 	  watchdog;

   // Outputs
   wire [63:0] 	  MemtoRegOut;
   wire [63:0] 	  currentPC;

   // Instantiate the Unit Under Test (UUT)
   singlecycle uut (
		    .CLK(CLK),
		    .resetl(Reset_L),
		    .startpc(startPC),
		    .currentpc(currentPC),
		    .MemtoRegOut(MemtoRegOut)
		    );

   initial begin
      // Initialize Inputs
      Reset_L = 1;
      startPC = 0;
      passed = 0;

      // Initialize Watchdog timer
      watchdog = 0;

      // Wait for global reset
      #(1 * `ClockPeriod);

      // Program 1
      #1
        Reset_L = 0; startPC = 0;
      @(posedge CLK);
      @(negedge CLK);
      @(posedge CLK);
      Reset_L = 1;

      // ***********************************************************
      // This while loop will continue cycling the processor until the
      // PC reaches the final instruction in the first test.  If the
      // program forms an infinite loop, never reaching the end, the
      // watchdog timer will kick in and kill simulation after 64K
      // cycles.
      // ***********************************************************

      while (currentPC < 64'h30)
        begin
	   @(posedge CLK);
	   @(negedge CLK);
           $display("CurrentPC:%h",currentPC);
        end
      passTest(MemtoRegOut, 64'hF, "Results of Program 1", passed);

      // ***********************************************************
      // Add your new tests here
      // ***********************************************************

      while (currentPC < 64'h54)
        begin
	   @(posedge CLK);
	   @(negedge CLK);
           $display("CurrentPC:%h",currentPC);
        end
      passTest(MemtoRegOut, 64'h123456789abcdef0, "Results of Program 2", passed);

      // Done
      allPassed(passed, 2);   // Be sure to change the one to match
      // the number of tests you add.
      $finish;
   end
   
   // Initialize the clock to be 0
   initial begin
      CLK = 0;
   end

   // The following is correct if clock starts at LOW level at StartTime //
   always begin
      #`HalfClockPeriod CLK = ~CLK;
      #`HalfClockPeriod CLK = ~CLK;
      watchdog = watchdog +1;
   end

   // Kill the simulation if the watchdog hits 64K cycles
   always @*
     if (watchdog == 16'hFF)
       begin
          $display("Watchdog Timer Expired.");
          $finish;
       end


endmodule

Lab06/Mux21.v
module Mux21 ( out , in , sel ) ;
	input [ 1 : 0 ] in ;
	input sel ;
	output out ;
	
	wire s_inv;
	wire a0, a1;
	
	not not1(s_inv, sel); // s_inv = !sel
	and and0(a0, s_inv, in[0]); // a0 = s_inv & in[0]
	and and1(a1, sel, in[1]); // a1 = sel & in[1]
	
	or or1(out, a0, a1); // out = a0 | a1
endmodule

Lab09/singlecycle.vcd
$date
	Tue Nov 28 16:37:09 2023
$end
$version
	Icarus Verilog
$end
$timescale
	1ps
$end
$scope module Mux21 $end
$var wire 1 ! a0 $end
$var wire 1 " a1 $end
$var wire 2 # in [1:0] $end
$var wire 1 $ out $end
$var wire 1 % s_inv $end
$var wire 1 & sel $end
$upscope $end
$scope module SingleCycleProcTest_v $end
$var wire 64 ' currentPC [63:0] $end
$var wire 64 ( MemtoRegOut [63:0] $end
$var reg 1 ) CLK $end
$var reg 1 * Reset_L $end
$var reg 8 + passed [7:0] $end
$var reg 64 , startPC [63:0] $end
$var reg 16 - watchdog [15:0] $end
$scope module uut $end
$var wire 1 ) CLK $end
$var wire 1 * resetl $end
$var wire 64 . startpc [63:0] $end
$var wire 1 / zero $end
$var wire 1 0 uncond_branch $end
$var wire 3 1 signop [2:0] $end
$var wire 5 2 rn [4:0] $end
$var wire 5 3 rm [4:0] $end
$var wire 1 4 regwrite $end
$var wire 64 5 regoutB [63:0] $end
$var wire 64 6 regoutA [63:0] $end
$var wire 1 7 reg2loc $end
$var wire 64 8 readOut [63:0] $end
$var wire 5 9 rd [4:0] $end
$var wire 64 : rb [63:0] $end
$var wire 11 ; opcode [10:0] $end
$var wire 64 < nextpc [63:0] $end
$var wire 1 = memwrite $end
$var wire 1 > memread $end
$var wire 1 ? mem2reg $end
$var wire 32 @ instruction [31:0] $end
$var wire 64 A extimm [63:0] $end
$var wire 1 B branch $end
$var wire 1 C alusrc $end
$var wire 64 D aluout [63:0] $end
$var wire 4 E aluctrl [3:0] $end
$var wire 64 F MemtoRegOut [63:0] $end
$var reg 64 G currentpc [63:0] $end
$scope module alu $end
$var wire 64 H BusB [63:0] $end
$var wire 1 / Zero $end
$var wire 64 I BusA [63:0] $end
$var wire 4 J ALUCtrl [3:0] $end
$var reg 64 K BusW [63:0] $end
$upscope $end
$scope module control $end
$var wire 11 L opcode [10:0] $end
$var reg 4 M aluop [3:0] $end
$var reg 1 C alusrc $end
$var reg 1 B branch $end
$var reg 1 ? mem2reg $end
$var reg 1 > memread $end
$var reg 1 = memwrite $end
$var reg 1 7 reg2loc $end
$var reg 1 4 regwrite $end
$var reg 3 N signop [2:0] $end
$var reg 1 0 uncond_branch $end
$upscope $end
$scope module dm $end
$var wire 64 O Address [63:0] $end
$var wire 1 ) Clock $end
$var wire 1 > MemoryRead $end
$var wire 1 = MemoryWrite $end
$var wire 64 P WriteData [63:0] $end
$var reg 64 Q ReadData [63:0] $end
$scope task initset $end
$var reg 64 R addr [63:0] $end
$var reg 64 S data [63:0] $end
$upscope $end
$upscope $end
$scope module imem $end
$var wire 64 T Address [63:0] $end
$var reg 32 U Data [31:0] $end
$upscope $end
$scope module mrf $end
$var wire 64 V BusW [63:0] $end
$var wire 1 ) Clk $end
$var wire 5 W RA [4:0] $end
$var wire 5 X RB [4:0] $end
$var wire 5 Y RW [4:0] $end
$var wire 1 4 RegWr $end
$var wire 64 Z BusB [63:0] $end
$var wire 64 [ BusA [63:0] $end
$upscope $end
$scope module npl $end
$var wire 1 / ALUZero $end
$var wire 1 B Branch $end
$var wire 64 \ CurrentPC [63:0] $end
$var wire 64 ] NextPC [63:0] $end
$var wire 1 0 Uncondbranch $end
$var wire 64 ^ SignExtImm64 [63:0] $end
$var reg 64 _ temp [63:0] $end
$upscope $end
$scope module see $end
$var wire 3 ` Ctrl [2:0] $end
$var wire 26 a Imm16 [25:0] $end
$var reg 64 b BusImm [63:0] $end
$upscope $end
$upscope $end
$scope task allPassed $end
$var reg 8 c numTests [7:0] $end
$var reg 8 d passed [7:0] $end
$upscope $end
$scope task passTest $end
$var reg 64 e actualOut [63:0] $end
$var reg 64 f expectedOut [63:0] $end
$var reg 8 g passed [7:0] $end
$var reg 257 h testType [256:0] $end
$upscope $end
$upscope $end
$enddefinitions $end
#0
$dumpvars
bx h
bx g
bx f
bx e
bx d
bx c
bx b
bx a
bx `
bx _
bx ^
bx ]
bx \
bx [
bx Z
bx Y
bx X
bx W
bx V
bx U
bx T
b0 S
b100000 R
bx Q
bx P
bx O
bx N
bx M
bx L
bx K
bx J
bx I
bx H
bx G
bx F
bx E
bx D
xC
xB
bx A
bx @
x?
x>
x=
bx <
bx ;
bx :
bx 9
bx 8
x7
bx 6
bx 5
x4
bx 3
bx 2
bx 1
x0
x/
b0 .
b0 -
b0 ,
b0 +
1*
0)
bx (
bx '
z&
z%
x$
bz #
x"
x!
$end
#60000
1)
#120000
b1 -
0)
#121000
0*
#180000
1)
#240000
b10 -
0)
#243000
1/
b0 D
b0 K
b0 O
b0 :
b0 H
b0 A
b0 ^
b0 b
b1 1
b1 N
b1 `
b10 E
b10 J
b10 M
00
0B
0=
1>
14
1?
1C
b0x00x 2
b0x00x X
b0 6
b0 I
b0 [
b10000000000001111101001 a
b11111000010 ;
b11111000010 L
b11111 3
b11111 W
b1001 9
b1001 Y
b11111000010000000000001111101001 @
b11111000010000000000001111101001 U
b100 <
b100 ]
b100 _
b0 '
b0 G
b0 T
b0 \
#300000
b1 (
b1 F
b1 V
b1 8
b1 Q
1*
1)
#360000
b11 -
0)
#363000
0/
b1000 D
b1000 K
b1000 O
b1000 :
b1000 H
b1000 A
b1000 ^
b1000 b
b0x0x0 2
b0x0x0 X
b10000001000001111101010 a
b1010 9
b1010 Y
b11111000010000001000001111101010 @
b11111000010000001000001111101010 U
b1000 <
b1000 ]
b1000 _
b100 '
b100 G
b100 T
b100 \
#420000
b1010 (
b1010 F
b1010 V
b1010 8
b1010 Q
1)
#480000
b100 -
0)
#483000
b10000 D
b10000 K
b10000 O
b10000 :
b10000 H
b10000 A
b10000 ^
b10000 b
b0x0x1 2
b0x0x1 X
b10000010000001111101011 a
b1011 9
b1011 Y
b11111000010000010000001111101011 @
b11111000010000010000001111101011 U
b1100 <
b1100 ]
b1100 _
b1000 '
b1000 G
b1000 T
b1000 \
#540000
b101 (
b101 F
b101 V
b101 8
b101 Q
1)
#600000
b101 -
0)
#603000
b11000 D
b11000 K
b11000 O
b11000 :
b11000 H
b11000 A
b11000 ^
b11000 b
b0xx0x 2
b0xx0x X
b10000011000001111101100 a
b1100 9
b1100 Y
b11111000010000011000001111101100 @
b11111000010000011000001111101100 U
b10000 <
b10000 ]
b10000 _
b1100 '
b1100 G
b1100 T
b1100 \
#660000
b111111111011111010100111110111101010110110111110111011111111 (
b111111111011111010100111110111101010110110111110111011111111 F
b111111111011111010100111110111101010110110111110111011111111 V
b111111111011111010100111110111101010110110111110111011111111 8
b111111111011111010100111110111101010110110111110111011111111 Q
1)
#720000
b110 -
0)
#723000
b100000 D
b100000 K
b100000 O
b100000 :
b100000 H
b100000 A
b100000 ^
b100000 b
b0xxxx 2
b0xxxx X
b10000100000001111101101 a
b1101 9
b1101 Y
b11111000010000100000001111101101 @
b11111000010000100000001111101101 U
b10100 <
b10100 ]
b10100 _
b10000 '
b10000 G
b10000 T
b10000 \
#780000
b0 (
b0 F
b0 V
b0 8
b0 Q
1)
#840000
b111 -
0)
#843000
b101 5
b101 P
b101 Z
b1111 (
b1111 F
b1111 V
b101 :
b101 H
b1111 D
b1111 K
b1111 O
b1111111111111111111111111111111111111000001011000000010100101000 A
b1111111111111111111111111111111111111000001011000000010100101000 ^
b1111111111111111111111111111111111111000001011000000010100101000 b
b1 E
b1 J
b1 M
b10 1
b10 N
b10 `
0>
0?
0C
07
b1011 2
b1011 X
b1010 6
b1010 I
b1010 [
b10000010110000000101001010 a
b10101010000 ;
b10101010000 L
b1010 3
b1010 W
b1010 9
b1010 Y
b10101010000010110000000101001010 @
b10101010000010110000000101001010 U
b11000 <
b11000 ]
b11000 _
b10100 '
b10100 G
b10100 T
b10100 \
#900000
1)
#960000
b1111 6
b1111 I
b1111 [
b1000 -
0)
#963000
b1111 :
b1111 H
b1111 (
b1111 F
b1111 V
b1111 5
b1111 P
b1111 Z
b1111 D
b1111 K
b1111 O
b1111111111111111111111111111111111111000001010000000011000110000 A
b1111111111111111111111111111111111111000001010000000011000110000 ^
b1111111111111111111111111111111111111000001010000000011000110000 b
b0 E
b0 J
b0 M
b1010 2
b1010 X
b111111111011111010100111110111101010110110111110111011111111 6
b111111111011111010100111110111101010110110111110111011111111 I
b111111111011111010100111110111101010110110111110111011111111 [
b10000010100000000110001100 a
b10001010000 ;
b10001010000 L
b1100 3
b1100 W
b1100 9
b1100 Y
b10001010000010100000000110001100 @
b10001010000010100000000110001100 U
b11100 <
b11100 ]
b11100 _
b11000 '
b11000 G
b11000 T
b11000 \
#1020000
1)
#1080000
b1111 6
b1111 I
b1111 [
b1001 -
0)
#1083000
0/
b1111 D
b1111 K
b1111 O
b1111 :
b1111 H
b0xxxx (
b0xxxx F
b0xxxx V
b1111 5
b1111 P
b1111 Z
b10000 A
b10000 ^
b10000 b
b11 1
b11 N
b11 `
b111 E
b111 J
b111 M
1B
04
x?
17
b1100 2
b1100 X
bx 6
bx I
bx [
b10001100 a
b10110100000 ;
b10110100000 L
b100 3
b100 W
b10110100000000000000000010001100 @
b10110100000000000000000010001100 U
b100000 <
b100000 ]
b100000 _
b11100 '
b11100 G
b11100 T
b11100 \
#1140000
1)
#1200000
b1010 -
0)
#1203000
0/
b1 D
b1 K
b1 O
b1 :
b1 H
b1 (
b1 F
b1 V
b1 5
b1 P
b1 Z
b1111111111111111111111111111111111111100001001000000011010110100 A
b1111111111111111111111111111111111111100001001000000011010110100 ^
b1111111111111111111111111111111111111100001001000000011010110100 b
b10 E
b10 J
b10 M
b10 1
b10 N
b10 `
0B
14
0?
07
b1001 2
b1001 X
b0 6
b0 I
b0 [
b11000010010000000110101101 a
b10001011000 ;
b10001011000 L
b1101 3
b1101 W
b1101 9
b1101 Y
b10001011000010010000000110101101 @
b10001011000010010000000110101101 U
b100100 <
b100100 ]
b100100 _
b100000 '
b100000 G
b100000 T
b100000 \
#1260000
1)
#1320000
b10 (
b10 F
b10 V
b10 D
b10 K
b10 O
b1 6
b1 I
b1 [
b1011 -
0)
