Lab06/HalfAdd.v
module HalfAdd (Cout, Sum, A, B);
	input A, B;
	output Cout, Sum;
	
	wire t1, t2, t3;
	
	// Omitting comments because taken from prelab
	
	//Cout (two NANDS to make an XOR)
	nand nand0(t1, A, B);
	nand nand1(Cout, t1, t1);
	
	//Sum (three NANDS to make an AND)
	nand nand3(t2, t1, A);
	nand nand4(t3, t1, B);
	nand nand5(Sum, t2, t3);
endmodule

Lab06/HalfAddTest.v
`timescale 1ns / 1ps

////////////////////////////////////////////////////////////////////////////////
// Company: 
// Engineer:
//
// Create Date:   15:12:10 03/02/2009
// Design Name:   HalfAdd
// Module Name:   E:/350/Lab6/HalfAdd/HalfAddTest.v
// Project Name:  HalfAdd
// Target Device:  
// Tool versions:  
// Description: 
//
// Verilog Test Fixture created by ISE for module: HalfAdd
//
// Dependencies:
// 
// Revision:
// Revision 0.01 - File Created
// Additional Comments:
// 
////////////////////////////////////////////////////////////////////////////////

`define STRLEN 15
module HalfAddTest_v;

   task passTest;
      input [1:0] actualOut, expectedOut;
      input [`STRLEN*8:0] testType;
      inout [7:0]         passed;
      
      if(actualOut == expectedOut) begin $display ("%s passed", testType); passed = passed + 1; end
      else $display ("%s failed: %d should be %d", testType, actualOut, expectedOut);
   endtask
   
   task allPassed;
      input [7:0] passed;
      input [7:0] numTests;
      
      if(passed == numTests) $display ("All tests passed");
      else $display("Some tests failed");
   endtask

   // Inputs
   reg            A;
   reg            B;
   reg [7:0]      passed;

   // Outputs
   wire           Cout;
   wire           Sum;

   // Instantiate the Device Under Test (DUT)
   HalfAdd dut (
		.Cout(Cout), 
		.Sum(Sum), 
		.A(A), 
		.B(B)
	        );
   initial begin
      $dumpfile("HalfAdd.vcd"); $dumpvars;
      end
      
   initial begin
      // Initialize Inputs
      A = 0;
      B = 0;
      passed = 0;

      // Add stimulus here
      #90; A=0;B=0; #10; passTest({Cout, Sum}, 0, "0+0", passed);
      #90; A=0;B=1; #10; passTest({Cout, Sum}, 1, "0+1", passed);
      #90; A=1;B=0; #10; passTest({Cout, Sum}, 1, "1+0", passed);
      #90; A=1;B=1; #10; passTest({Cout, Sum}, 2, "1+1", passed);
      #90;
      
      allPassed(passed, 4);

   end
   
endmodule

Lab06/HalfAdd.vcd
$date
	Tue Oct 17 15:56:50 2023
$end
$version
	Icarus Verilog
$end
$timescale
	1ps
$end
$scope module HalfAddTest_v $end
$var wire 1 ! Sum $end
$var wire 1 " Cout $end
$var reg 1 # A $end
$var reg 1 $ B $end
$var reg 8 % passed [7:0] $end
$scope module dut $end
$var wire 1 # A $end
$var wire 1 $ B $end
$var wire 1 " Cout $end
$var wire 1 ! Sum $end
$var wire 1 & t1 $end
$var wire 1 ' t2 $end
$var wire 1 ( t3 $end
$upscope $end
$scope task allPassed $end
$var reg 8 ) numTests [7:0] $end
$var reg 8 * passed [7:0] $end
$upscope $end
$scope task passTest $end
$var reg 2 + actualOut [1:0] $end
$var reg 2 , expectedOut [1:0] $end
$var reg 8 - passed [7:0] $end
$var reg 121 . testType [120:0] $end
$upscope $end
$upscope $end
$enddefinitions $end
#0
$dumpvars
bx .
bx -
bx ,
bx +
bx *
bx )
1(
1'
1&
b0 %
0$
0#
0"
0!
$end
#100000
b1 %
b1 -
b1100000010101100110000 .
b0 ,
b0 +
#190000
1!
0(
1$
#200000
b10 %
b10 -
b1100000010101100110001 .
b1 ,
b1 +
#290000
1(
0'
0$
1#
#300000
b11 %
b11 -
b1100010010101100110000 .
#390000
0!
1"
1'
0&
1(
1$
#400000
b100 %
b100 -
b1100010010101100110001 .
b10 ,
b10 +
#490000
b100 )
b100 *
